prettytable-stubs/METADATA.toml
prettytable-stubs/__init__.pyi
prettytable-stubs/colortable.pyi
prettytable-stubs/prettytable.pyi
types_prettytable-3.4.2.5.dist-info/METADATA
types_prettytable-3.4.2.5.dist-info/WHEEL
types_prettytable-3.4.2.5.dist-info/top_level.txt
types_prettytable-3.4.2.5.dist-info/RECORD
